collectiontools/__init__.py
collectiontools-0.2.3.dist-info/licenses/LICENSE
collectiontools-0.2.3.dist-info/METADATA
collectiontools-0.2.3.dist-info/WHEEL
collectiontools-0.2.3.dist-info/top_level.txt
collectiontools-0.2.3.dist-info/RECORD
